here_oauth/__init__.py
here_oauth/here_oauth.py
here_oauth-0.0.2.dist-info/LICENSE
here_oauth-0.0.2.dist-info/METADATA
here_oauth-0.0.2.dist-info/WHEEL
here_oauth-0.0.2.dist-info/top_level.txt
here_oauth-0.0.2.dist-info/RECORD
