Metadata-Version: 2.1
Name: here-oauth
Version: 0.0.2
Summary: oauth for HERE Technologies API
Home-page: https://github.com/spara/here_oauth
Author: Sophia Parafina
Author-email: sophia.parafina@gmail.com
License: UNKNOWN
Project-URL: Bug Tracker, https://github.com/spara/here_oauth/issues
Platform: UNKNOWN
Classifier: Programming Language :: Python :: 3
Classifier: License :: OSI Approved :: MIT License
Classifier: Operating System :: OS Independent
Requires-Python: >=3.6
License-File: LICENSE
